nyc_records_common/__init__.py
nyc_records_common/cloud/__init__.py
nyc_records_common/cloud/secrets.py
nyc_records_common/utils/__init__.py
nyc_records_common/utils/db_utils.py
nyc_records_common/utils/error_handler.py
nyc_records_common/utils/fs.py
nyc_records_common/utils/time.py
nyc_records_db/__init__.py
nyc_records_db/config/__init__.py
nyc_records_db/config/settings.py
nyc_records_db/db/session.py
nyc_records_db/migrations/__init__.py
nyc_records_db/migrations/env.py
nyc_records_db/models/__init__.py
nyc_records_db/models/base.py
nyc_records_db/models/tables/__init__.py
nyc_records_db/models/tables/nyc_asset_details.py
nyc_records_common-0.1.29.dist-info/LICENSE
nyc_records_common-0.1.29.dist-info/METADATA
nyc_records_common-0.1.29.dist-info/WHEEL
nyc_records_common-0.1.29.dist-info/top_level.txt
nyc_records_common-0.1.29.dist-info/RECORD
