Metadata-Version: 2.2
Name: nyc_records_common
Version: 0.1.29
Summary: Common utilities for NYC Records Scraper
Author: Stuart Shay
Project-URL: Source, https://github.com/stuartshay/nyc_records_scraper
Classifier: Development Status :: 3 - Alpha
Classifier: Intended Audience :: Developers
Classifier: Programming Language :: Python :: 3.11
Requires-Python: >=3.11
License-File: LICENSE
Requires-Dist: google-cloud-secret-manager>=2.22.0
Requires-Dist: google-api-core>=2.24.0
Requires-Dist: google-auth>=2.37.0
Requires-Dist: humanize>=4.9.0
Requires-Dist: protobuf>=4.25.3
Requires-Dist: grpcio>=1.62.1
